README.md
setup.cfg
setup.py
agilentlightwave/__init__.py
agilentlightwave/agilent_8164B_laser.py
agilentlightwave/agilent_8164B_power_meter.py
agilentlightwave/agilent_lightwave.py
agilentlightwave/agilent_lightwave_connection.py
agilentlightwave/laser.py
agilentlightwave/power_meter.py
agilentlightwave.egg-info/PKG-INFO
agilentlightwave.egg-info/SOURCES.txt
agilentlightwave.egg-info/dependency_links.txt
agilentlightwave.egg-info/not-zip-safe
agilentlightwave.egg-info/requires.txt
agilentlightwave.egg-info/top_level.txt